{
  "$schema": "https://schemas.r3e.network/miniapp-manifest/v1.json",
  "id": "miniapp-dailycheckin",
  "name": "Daily Check-in",
  "version": "1.0.0",
  "description": "Daily check-in rewards and streak tracking",
  "category": "games",
  "tags": [
    "rewards",
    "daily",
    "streak"
  ],
  "developer": {
    "name": "R3E Network",
    "email": "dev@r3e.network",
    "website": "https://r3e.network"
  },
  "contracts": {
    "primary": "0x908867b23ab551a598723ceeaaedd70c54e10c76"
  },
  "urls": {
    "entry": "/miniapps/daily-checkin/index.html",
    "icon": "/miniapps/daily-checkin/logo.png",
    "banner": "/miniapps/daily-checkin/banner.png"
  },
  "permissions": [
    "invoke:primary",
    "read:blockchain"
  ],
  "features": {
    "stateless": true,
    "offlineSupport": false,
    "deeplink": "neomainapp://daily-checkin"
  },
  "stateSource": {
    "type": "smart-contract",
    "chain": "neo-n3-mainnet",
    "endpoints": [
      "https://neoxrpc1.blackholelabs.io"
    ]
  },
  "platform": {
    "analytics": true,
    "comments": true,
    "ratings": true,
    "transactions": true
  },
  "createdAt": "2026-01-01T00:00:00Z",
  "updatedAt": "2026-01-26T00:00:00Z"
}